AUTHORS.rst
CONTRIBUTING.rst
HISTORY.rst
LICENSE
MANIFEST.in
README.md
setup.cfg
setup.py
docs/Makefile
docs/authors.rst
docs/conf.py
docs/contributing.rst
docs/history.rst
docs/index.rst
docs/installation.rst
docs/make.bat
docs/readme.rst
docs/usage.rst
pyparallel/__init__.py
pyparallel/cli.py
pyparallel/pyparallel.py
split_downloader.egg-info/PKG-INFO
split_downloader.egg-info/SOURCES.txt
split_downloader.egg-info/dependency_links.txt
split_downloader.egg-info/entry_points.txt
split_downloader.egg-info/not-zip-safe
split_downloader.egg-info/requires.txt
split_downloader.egg-info/top_level.txt
tests/conftest.py
tests/test_pyparallel.py