Metadata-Version: 2.1
Name: split-downloader
Version: 0.2.5
Summary: Parallel downloader
Home-page: https://github.com/joeirimpan/pyparallel
Author: Joe Paul
Author-email: joeirimpan@gmail.com
License: MIT license
Keywords: pyparallel
Platform: UNKNOWN
Classifier: Development Status :: 2 - Pre-Alpha
Classifier: Intended Audience :: Developers
Classifier: License :: OSI Approved :: MIT License
Classifier: Natural Language :: English
Classifier: Programming Language :: Python :: 2
Classifier: Programming Language :: Python :: 2.6
Classifier: Programming Language :: Python :: 2.7
Classifier: Programming Language :: Python :: 3
Classifier: Programming Language :: Python :: 3.3
Classifier: Programming Language :: Python :: 3.4
Classifier: Programming Language :: Python :: 3.5
